chaosiq/__init__.py
chaosiq/__main__.py
chaosiq/api.py
chaosiq/cli.py
chaosiq/cli_overload.py
chaosiq/config.py
chaosiq/exceptions.py
chaosiq/types.py
chaosiq/discovery/__init__.py
chaosiq/discovery/cf.py
chaosiq/discovery/k8s.py
chaosiq-0.9.0.dist-info/DESCRIPTION.rst
chaosiq-0.9.0.dist-info/METADATA
chaosiq-0.9.0.dist-info/RECORD
chaosiq-0.9.0.dist-info/WHEEL
chaosiq-0.9.0.dist-info/entry_points.txt
chaosiq-0.9.0.dist-info/metadata.json
chaosiq-0.9.0.dist-info/top_level.txt
