Metadata-Version: 2.0
Name: chaosiq
Version: 0.9.0
Summary: ChaosIQ plugins for the Chaos Toolkit project
Home-page: http://www.chaosiq.io
Author: chaosiq, inc
Author-email: support@chaosiq.io
License: Apache License Version 2.0
Platform: UNKNOWN
Classifier: Intended Audience :: Developers
Classifier: License :: Freely Distributable
Classifier: Operating System :: OS Independent
Classifier: License :: OSI Approved :: Apache Software License
Classifier: Programming Language :: Python
Classifier: Programming Language :: Python :: 3
Classifier: Programming Language :: Python :: 3.5
Classifier: Programming Language :: Python :: 3.6
Classifier: Programming Language :: Python :: Implementation
Classifier: Programming Language :: Python :: Implementation :: CPython
Requires-Python: >=3.5.*
Requires-Dist: chaostoolkit-lib (>=0.14.0)
Requires-Dist: chaostoolkit (>=0.10.0)
Requires-Dist: click
Requires-Dist: logzero
Requires-Dist: requests
Requires-Dist: simplejson
Requires-Dist: pyyaml
